mobilitymapper/__init__.py
mobilitymapper/fsw.py
mobility_mapper-0.0.13.dist-info/LICENSE
mobility_mapper-0.0.13.dist-info/METADATA
mobility_mapper-0.0.13.dist-info/WHEEL
mobility_mapper-0.0.13.dist-info/top_level.txt
mobility_mapper-0.0.13.dist-info/RECORD
