Metadata-Version: 2.1
Name: mobility-mapper
Version: 0.0.13
Summary: For manually scoring mobility in behavior tests
Home-page: https://github.com/researchgrant/mobility-mapper/
Author: Grant Weiss
Author-email: grant.weiss@me.com
License: UNKNOWN
Platform: UNKNOWN
Classifier: Programming Language :: Python :: 3
Classifier: License :: OSI Approved :: MIT License
Classifier: Operating System :: OS Independent
Requires-Python: >=3.6
Requires-Dist: numpy
Requires-Dist: pandas
Requires-Dist: opencv-python
Requires-Dist: PyQt5 (<=5.12)
Requires-Dist: pyqtgraph
Requires-Dist: pyqtwebengine (<=5.12)
